traligner/__init__.py
traligner/alignment_tools.py
traligner/text_alignment_clean.py
traligner-0.2.3.dist-info/licenses/LICENSE
traligner-0.2.3.dist-info/METADATA
traligner-0.2.3.dist-info/WHEEL
traligner-0.2.3.dist-info/top_level.txt
traligner-0.2.3.dist-info/RECORD
