Metadata-Version: 2.4
Name: traligner
Version: 0.2.3
Summary: Text Reuse Alignment for Hebrew and multi-language texts
Home-page: https://github.com/millerhadar/traligner
Author: Hadar Miller
Author-email: Hadar Miller <hadar.miller@example.com>
License: MIT
Project-URL: Homepage, https://github.com/millerhadar/traligner
Project-URL: Documentation, https://github.com/millerhadar/traligner#readme
Project-URL: Repository, https://github.com/millerhadar/traligner
Project-URL: Bug Tracker, https://github.com/millerhadar/traligner/issues
Keywords: text-reuse,alignment,hebrew,nlp,linguistics,text-analysis
Classifier: Development Status :: 4 - Beta
Classifier: Intended Audience :: Science/Research
Classifier: License :: OSI Approved :: MIT License
Classifier: Programming Language :: Python :: 3
Classifier: Programming Language :: Python :: 3.8
Classifier: Programming Language :: Python :: 3.9
Classifier: Programming Language :: Python :: 3.10
Classifier: Programming Language :: Python :: 3.11
Requires-Python: >=3.8
License-File: LICENSE
Requires-Dist: numpy>=1.20.0
Requires-Dist: pandas>=1.3.0
Requires-Dist: rapidfuzz>=2.0.0
Provides-Extra: dev
Requires-Dist: pytest>=6.0; extra == "dev"
Requires-Dist: pytest-cov>=2.0; extra == "dev"
Requires-Dist: black>=21.0; extra == "dev"
Requires-Dist: flake8>=3.9; extra == "dev"
Provides-Extra: elasticsearch
Requires-Dist: elasticsearch<9.0.0,>=7.0.0; extra == "elasticsearch"
Dynamic: author
Dynamic: home-page
Dynamic: license-file
Dynamic: requires-python
